openjson/__init__.py
openjson/api.py
openjson/encoding/__init__.py
openjson/encoding/encode.py
openjson/loading/__init__.py
openjson/saving/__init__.py
openjson-0.1.0.dist-info/LICENSE.md
openjson-0.1.0.dist-info/METADATA
openjson-0.1.0.dist-info/WHEEL
openjson-0.1.0.dist-info/top_level.txt
openjson-0.1.0.dist-info/RECORD
